LICENSE
MANIFEST.in
README
setup.py
tests.py
Flask_Script.egg-info/PKG-INFO
Flask_Script.egg-info/SOURCES.txt
Flask_Script.egg-info/dependency_links.txt
Flask_Script.egg-info/namespace_packages.txt
Flask_Script.egg-info/not-zip-safe
Flask_Script.egg-info/requires.txt
Flask_Script.egg-info/top_level.txt
docs/Makefile
docs/conf.py
docs/index.rst
docs/make.bat
docs/_static/flask-script.png
docs/_themes/README
docs/_themes/flask_theme_support.py
docs/_themes/flask/theme.conf
docs/_themes/flask/static/flasky.css_t
docs/_themes/flask_small/layout.html
docs/_themes/flask_small/theme.conf
docs/_themes/flask_small/static/flasky.css_t
docs/output/.buildinfo
docs/output/genindex.html
docs/output/index.html
docs/output/objects.inv
docs/output/py-modindex.html
docs/output/search.html
docs/output/searchindex.js
docs/output/.doctrees/environment.pickle
docs/output/.doctrees/index.doctree
docs/output/_sources/index.txt
docs/output/_static/basic.css
docs/output/_static/doctools.js
docs/output/_static/file.png
docs/output/_static/flask-script.png
docs/output/_static/flasky.css
docs/output/_static/jquery.js
docs/output/_static/minus.png
docs/output/_static/plus.png
docs/output/_static/pygments.css
docs/output/_static/searchtools.js
docs/output/_static/underscore.js
flaskext/__init__.py
flaskext/script.py