Metadata-Version: 1.0
Name: Flask-Script
Version: 0.3
Summary: Scripting support for Flask
Home-page: http://bitbucket.org/danjac/flask-script
Author: Dan Jacob
Author-email: danjac354@gmail.com
License: BSD
Platform: any
Classifier: Development Status :: 4 - Beta
Classifier: Environment :: Web Environment
Classifier: Intended Audience :: Developers
Classifier: License :: OSI Approved :: BSD License
Classifier: Operating System :: OS Independent
Classifier: Programming Language :: Python
Classifier: Topic :: Internet :: WWW/HTTP :: Dynamic Content
Classifier: Topic :: Software Development :: Libraries :: Python Modules
